cmac/__init__.py
cmac/mac_lookup.py
cmac-1.0.0.dist-info/LICENSE
cmac-1.0.0.dist-info/METADATA
cmac-1.0.0.dist-info/WHEEL
cmac-1.0.0.dist-info/top_level.txt
cmac-1.0.0.dist-info/RECORD
