Metadata-Version: 2.1
Name: cmac
Version: 1.0.0
Summary: UNKNOWN
Home-page: UNKNOWN
Author: Jacob H Barrow
Author-email: jacob.h.barrow@gmail.com
License: MIT
Platform: UNKNOWN
Classifier: License :: OSI Approved :: MIT License
Classifier: Programming Language :: Python
Classifier: Programming Language :: Python :: 3
License-File: LICENSE
